{
"meta":{"test_sets":[],"test_metrics":[],"learn_metrics":[{"best_value":"Min","name":"Logloss"}],"launch_mode":"Train","parameters":"","iteration_count":200,"learn_sets":["learn"],"name":"experiment"},
"iterations":[
{"learn":[0.6773767697],"iteration":0,"passed_time":0.005968097061,"remaining_time":1.187651315},
{"learn":[0.6648358707],"iteration":1,"passed_time":0.01151735398,"remaining_time":1.140218044},
{"learn":[0.654648615],"iteration":2,"passed_time":0.01753782689,"remaining_time":1.151650632},
{"learn":[0.6454916508],"iteration":3,"passed_time":0.02336775504,"remaining_time":1.145019997},
{"learn":[0.6390820637],"iteration":4,"passed_time":0.02878255143,"remaining_time":1.122519506},
{"learn":[0.6323711876],"iteration":5,"passed_time":0.03381250824,"remaining_time":1.0932711},
{"learn":[0.6270297828],"iteration":6,"passed_time":0.03942309948,"remaining_time":1.086951171},
{"learn":[0.6213832489],"iteration":7,"passed_time":0.04486293795,"remaining_time":1.076710511},
{"learn":[0.6162643975],"iteration":8,"passed_time":0.05009385636,"remaining_time":1.063102952},
{"learn":[0.6124061155],"iteration":9,"passed_time":0.05654762799,"remaining_time":1.074404932},
{"learn":[0.6084577005],"iteration":10,"passed_time":0.06209730158,"remaining_time":1.066944545},
{"learn":[0.6056589556],"iteration":11,"passed_time":0.06758609918,"remaining_time":1.058848887},
{"learn":[0.6026862085],"iteration":12,"passed_time":0.07296602,"remaining_time":1.049588134},
{"learn":[0.6000078633],"iteration":13,"passed_time":0.07868802973,"remaining_time":1.045426681},
{"learn":[0.5980097701],"iteration":14,"passed_time":0.08476550357,"remaining_time":1.045441211},
{"learn":[0.5952354486],"iteration":15,"passed_time":0.09044492927,"remaining_time":1.040116687},
{"learn":[0.593051215],"iteration":16,"passed_time":0.09600806141,"remaining_time":1.033498543},
{"learn":[0.5915549545],"iteration":17,"passed_time":0.1014017741,"remaining_time":1.025284605},
{"learn":[0.5894098584],"iteration":18,"passed_time":0.1068878634,"remaining_time":1.01824754},
{"learn":[0.5877450024],"iteration":19,"passed_time":0.1118216519,"remaining_time":1.006394867},
{"learn":[0.5863815001],"iteration":20,"passed_time":0.1169511103,"remaining_time":0.9968689882},
{"learn":[0.5845701368],"iteration":21,"passed_time":0.1221542783,"remaining_time":0.9883391608},
{"learn":[0.582730901],"iteration":22,"passed_time":0.1271872768,"remaining_time":0.9787890434},
{"learn":[0.581458014],"iteration":23,"passed_time":0.13260924,"remaining_time":0.97246776},
{"learn":[0.5800838426],"iteration":24,"passed_time":0.1380950376,"remaining_time":0.9666652629},
{"learn":[0.5789095822],"iteration":25,"passed_time":0.1431217443,"remaining_time":0.9578147503},
{"learn":[0.5776751075],"iteration":26,"passed_time":0.148327454,"remaining_time":0.9503944273},
{"learn":[0.5761657071],"iteration":27,"passed_time":0.1534378704,"remaining_time":0.9425469182},
{"learn":[0.5750614946],"iteration":28,"passed_time":0.1588316665,"remaining_time":0.9365591367},
{"learn":[0.5741299802],"iteration":29,"passed_time":0.1639940421,"remaining_time":0.9292995718},
{"learn":[0.5731059261],"iteration":30,"passed_time":0.1684666982,"remaining_time":0.9184152255},
{"learn":[0.5721261814],"iteration":31,"passed_time":0.1733614444,"remaining_time":0.9101475833},
{"learn":[0.5712298684],"iteration":32,"passed_time":0.178171856,"remaining_time":0.9016575743},
{"learn":[0.5703807354],"iteration":33,"passed_time":0.1829205582,"remaining_time":0.8930827255},
{"learn":[0.5696130137],"iteration":34,"passed_time":0.1877040944,"remaining_time":0.8848907306},
{"learn":[0.5688127829],"iteration":35,"passed_time":0.1928903454,"remaining_time":0.8787226845},
{"learn":[0.5680105988],"iteration":36,"passed_time":0.1982822664,"remaining_time":0.8735137682},
{"learn":[0.5669800689],"iteration":37,"passed_time":0.2034830593,"remaining_time":0.8674804108},
{"learn":[0.5662811517],"iteration":38,"passed_time":0.2088939806,"remaining_time":0.8623572022},
{"learn":[0.565220907],"iteration":39,"passed_time":0.2142600679,"remaining_time":0.8570402717},
{"learn":[0.5646360892],"iteration":40,"passed_time":0.2188191421,"remaining_time":0.848591307},
{"learn":[0.563896174],"iteration":41,"passed_time":0.2242533554,"remaining_time":0.8436197657},
{"learn":[0.5630504895],"iteration":42,"passed_time":0.2292826456,"remaining_time":0.837148264},
{"learn":[0.56232664],"iteration":43,"passed_time":0.2343563948,"remaining_time":0.830899945},
{"learn":[0.5614690504],"iteration":44,"passed_time":0.2399722361,"remaining_time":0.8265710354},
{"learn":[0.5608196394],"iteration":45,"passed_time":0.2447076048,"remaining_time":0.8192385029},
{"learn":[0.5600922164],"iteration":46,"passed_time":0.2500676919,"remaining_time":0.8140501461},
{"learn":[0.5592993431],"iteration":47,"passed_time":0.2552643181,"remaining_time":0.8083370074},
{"learn":[0.5587792184],"iteration":48,"passed_time":0.2607034482,"remaining_time":0.8033922589},
{"learn":[0.5582955609],"iteration":49,"passed_time":0.2653676908,"remaining_time":0.7961030723},
{"learn":[0.5577169075],"iteration":50,"passed_time":0.2703952309,"remaining_time":0.7899782235},
{"learn":[0.5572966068],"iteration":51,"passed_time":0.275607149,"remaining_time":0.784420347},
{"learn":[0.5568405759],"iteration":52,"passed_time":0.280587605,"remaining_time":0.7782335458},
{"learn":[0.5562478896],"iteration":53,"passed_time":0.2855998115,"remaining_time":0.7721772681},
{"learn":[0.55578456],"iteration":54,"passed_time":0.2908977726,"remaining_time":0.7669123097},
{"learn":[0.5551776817],"iteration":55,"passed_time":0.2962795268,"remaining_time":0.7618616404},
{"learn":[0.5547506794],"iteration":56,"passed_time":0.3015117369,"remaining_time":0.7564241821},
{"learn":[0.5540793186],"iteration":57,"passed_time":0.3067780309,"remaining_time":0.7510772481},
{"learn":[0.5536859662],"iteration":58,"passed_time":0.3121782021,"remaining_time":0.7460529914},
{"learn":[0.5532901924],"iteration":59,"passed_time":0.3173261608,"remaining_time":0.7404277085},
{"learn":[0.5527970599],"iteration":60,"passed_time":0.3228155834,"remaining_time":0.7355961654},
{"learn":[0.5523250778],"iteration":61,"passed_time":0.3284036326,"remaining_time":0.7309629242},
{"learn":[0.5519704501],"iteration":62,"passed_time":0.3334352561,"remaining_time":0.7250893664},
{"learn":[0.5516419985],"iteration":63,"passed_time":0.3388054684,"remaining_time":0.7199616204},
{"learn":[0.5511478012],"iteration":64,"passed_time":0.3436545473,"remaining_time":0.7137440598},
{"learn":[0.5507107584],"iteration":65,"passed_time":0.3488591319,"remaining_time":0.7082897527},
{"learn":[0.5503289335],"iteration":66,"passed_time":0.3537517532,"remaining_time":0.7022236295},
{"learn":[0.5498445957],"iteration":67,"passed_time":0.3590135054,"remaining_time":0.6969085694},
{"learn":[0.5495047263],"iteration":68,"passed_time":0.3642472155,"remaining_time":0.691541815},
{"learn":[0.5491282177],"iteration":69,"passed_time":0.3694292165,"remaining_time":0.6860828306},
{"learn":[0.5487312716],"iteration":70,"passed_time":0.374504174,"remaining_time":0.6804371612},
{"learn":[0.5482514529],"iteration":71,"passed_time":0.3797205922,"remaining_time":0.6750588306},
{"learn":[0.547620885],"iteration":72,"passed_time":0.3845685877,"remaining_time":0.6690439813},
{"learn":[0.5471423965],"iteration":73,"passed_time":0.3899432584,"remaining_time":0.6639574401},
{"learn":[0.5468513063],"iteration":74,"passed_time":0.3950425914,"remaining_time":0.658404319},
{"learn":[0.5465193018],"iteration":75,"passed_time":0.4000880484,"remaining_time":0.6527752369},
{"learn":[0.5460373151],"iteration":76,"passed_time":0.4046858315,"remaining_time":0.6464461984},
{"learn":[0.5455270123],"iteration":77,"passed_time":0.4098991663,"remaining_time":0.6411243371},
{"learn":[0.5448376911],"iteration":78,"passed_time":0.4146051179,"remaining_time":0.6350280919},
{"learn":[0.5445449064],"iteration":79,"passed_time":0.4199584966,"remaining_time":0.6299377449},
{"learn":[0.5439012201],"iteration":80,"passed_time":0.4252908333,"remaining_time":0.6248099897},
{"learn":[0.5435902729],"iteration":81,"passed_time":0.4303650825,"remaining_time":0.6193058504},
{"learn":[0.5432715718],"iteration":82,"passed_time":0.4356027927,"remaining_time":0.6140424909},
{"learn":[0.5429461162],"iteration":83,"passed_time":0.4409009622,"remaining_time":0.6088632335},
{"learn":[0.5426539078],"iteration":84,"passed_time":0.4460697129,"remaining_time":0.6035060822},
{"learn":[0.5424167027],"iteration":85,"passed_time":0.4511634624,"remaining_time":0.598053892},
{"learn":[0.5421434891],"iteration":86,"passed_time":0.4562257948,"remaining_time":0.5925691357},
{"learn":[0.54186842],"iteration":87,"passed_time":0.4616858836,"remaining_time":0.5876002154},
{"learn":[0.5415124324],"iteration":88,"passed_time":0.4668465925,"remaining_time":0.5822468738},
{"learn":[0.541172215],"iteration":89,"passed_time":0.4720555522,"remaining_time":0.576956786},
{"learn":[0.5407702296],"iteration":90,"passed_time":0.4772968041,"remaining_time":0.571707161},
{"learn":[0.5403241356],"iteration":91,"passed_time":0.4824931803,"remaining_time":0.5664050377},
{"learn":[0.5398627122],"iteration":92,"passed_time":0.4878377672,"remaining_time":0.5612757107},
{"learn":[0.5394637635],"iteration":93,"passed_time":0.4925863028,"remaining_time":0.5554696606},
{"learn":[0.5390468462],"iteration":94,"passed_time":0.4979883073,"remaining_time":0.5504081291},
{"learn":[0.5386850832],"iteration":95,"passed_time":0.5033027687,"remaining_time":0.5452446661},
{"learn":[0.5383974868],"iteration":96,"passed_time":0.5088702343,"remaining_time":0.5403467436},
{"learn":[0.5381039324],"iteration":97,"passed_time":0.5145599518,"remaining_time":0.5355623988},
{"learn":[0.5378372812],"iteration":98,"passed_time":0.5197860368,"remaining_time":0.5302867648},
{"learn":[0.5375380423],"iteration":99,"passed_time":0.5253859612,"remaining_time":0.5253859612},
{"learn":[0.537096762],"iteration":100,"passed_time":0.5306063378,"remaining_time":0.5200992816},
{"learn":[0.5366478098],"iteration":101,"passed_time":0.5356095025,"remaining_time":0.5146052082},
{"learn":[0.5362132456],"iteration":102,"passed_time":0.5407972118,"remaining_time":0.5092944616},
{"learn":[0.5357520295],"iteration":103,"passed_time":0.5463564272,"remaining_time":0.5043290098},
{"learn":[0.5355120149],"iteration":104,"passed_time":0.5513360082,"remaining_time":0.498827817},
{"learn":[0.5351221769],"iteration":105,"passed_time":0.5567712633,"remaining_time":0.4937405542},
{"learn":[0.5346916949],"iteration":106,"passed_time":0.5619511809,"remaining_time":0.4884248581},
{"learn":[0.5343366279],"iteration":107,"passed_time":0.5679012776,"remaining_time":0.483767755},
{"learn":[0.5341186261],"iteration":108,"passed_time":0.5733531996,"remaining_time":0.4786710199},
{"learn":[0.5338126634],"iteration":109,"passed_time":0.5785169503,"remaining_time":0.4733320502},
{"learn":[0.5335048639],"iteration":110,"passed_time":0.5834435721,"remaining_time":0.4678061073},
{"learn":[0.5330617459],"iteration":111,"passed_time":0.5885200296,"remaining_time":0.4624085947},
{"learn":[0.532653251],"iteration":112,"passed_time":0.593708489,"remaining_time":0.457102996},
{"learn":[0.5321611843],"iteration":113,"passed_time":0.5992360789,"remaining_time":0.4520552876},
{"learn":[0.531667394],"iteration":114,"passed_time":0.6048671288,"remaining_time":0.4470757039},
{"learn":[0.5312579193],"iteration":115,"passed_time":0.6104329693,"remaining_time":0.4420376675},
{"learn":[0.5308768093],"iteration":116,"passed_time":0.6156809714,"remaining_time":0.4367651335},
{"learn":[0.5304902345],"iteration":117,"passed_time":0.6212430618,"remaining_time":0.4317112802},
{"learn":[0.5301111503],"iteration":118,"passed_time":0.6266721501,"remaining_time":0.4265583543},
{"learn":[0.5297546777],"iteration":119,"passed_time":0.6319249022,"remaining_time":0.4212832681},
{"learn":[0.5294027427],"iteration":120,"passed_time":0.6372085715,"remaining_time":0.4160287367},
{"learn":[0.5290408789],"iteration":121,"passed_time":0.6421949026,"remaining_time":0.4105836262},
{"learn":[0.5287043513],"iteration":122,"passed_time":0.6480898318,"remaining_time":0.4057147727},
{"learn":[0.5282732372],"iteration":123,"passed_time":0.6530329955,"remaining_time":0.4002460295},
{"learn":[0.5279154366],"iteration":124,"passed_time":0.6581596205,"remaining_time":0.3948957723},
{"learn":[0.5276187263],"iteration":125,"passed_time":0.6635275412,"remaining_time":0.3896907781},
{"learn":[0.5273403366],"iteration":126,"passed_time":0.6687117088,"remaining_time":0.3843775964},
{"learn":[0.5268674199],"iteration":127,"passed_time":0.6732777414,"remaining_time":0.3787187295},
{"learn":[0.5265302073],"iteration":128,"passed_time":0.6784656174,"remaining_time":0.3734190608},
{"learn":[0.5261736329],"iteration":129,"passed_time":0.6839410398,"remaining_time":0.3682759445},
{"learn":[0.5257764244],"iteration":130,"passed_time":0.6893441277,"remaining_time":0.363089655},
{"learn":[0.5253647036],"iteration":131,"passed_time":0.6946231302,"remaining_time":0.357836158},
{"learn":[0.5251168477],"iteration":132,"passed_time":0.7000361349,"remaining_time":0.3526497823},
{"learn":[0.5247319955],"iteration":133,"passed_time":0.7054825568,"remaining_time":0.3474764832},
{"learn":[0.5243654233],"iteration":134,"passed_time":0.7110122718,"remaining_time":0.342339242},
{"learn":[0.5240261496],"iteration":135,"passed_time":0.7159714774,"remaining_time":0.3369277541},
{"learn":[0.5236961748],"iteration":136,"passed_time":0.721297814,"remaining_time":0.3316916955},
{"learn":[0.523257127],"iteration":137,"passed_time":0.7263901052,"remaining_time":0.3263491777},
{"learn":[0.5229429492],"iteration":138,"passed_time":0.7312523926,"remaining_time":0.3209093234},
{"learn":[0.5225943029],"iteration":139,"passed_time":0.7366485637,"remaining_time":0.3157065273},
{"learn":[0.5222557976],"iteration":140,"passed_time":0.7419306079,"remaining_time":0.3104532331},
{"learn":[0.5218624348],"iteration":141,"passed_time":0.7462468031,"remaining_time":0.3048050323},
{"learn":[0.5215641419],"iteration":142,"passed_time":0.751322594,"remaining_time":0.2994782368},
{"learn":[0.5212000094],"iteration":143,"passed_time":0.7565081783,"remaining_time":0.2941976249},
{"learn":[0.5207810941],"iteration":144,"passed_time":0.7620711438,"remaining_time":0.2890614683},
{"learn":[0.5204418517],"iteration":145,"passed_time":0.7673392295,"remaining_time":0.2838104},
{"learn":[0.5201151329],"iteration":146,"passed_time":0.7727806097,"remaining_time":0.2786215804},
{"learn":[0.5197247235],"iteration":147,"passed_time":0.7780443619,"remaining_time":0.273366938},
{"learn":[0.5193387889],"iteration":148,"passed_time":0.7831014858,"remaining_time":0.2680414482},
{"learn":[0.5189552912],"iteration":149,"passed_time":0.7884220307,"remaining_time":0.2628073436},
{"learn":[0.5185464298],"iteration":150,"passed_time":0.7936529491,"remaining_time":0.25754301},
{"learn":[0.5180408147],"iteration":151,"passed_time":0.7991506635,"remaining_time":0.2523633674},
{"learn":[0.5176955852],"iteration":152,"passed_time":0.8042773302,"remaining_time":0.2470655851},
{"learn":[0.5173404351],"iteration":153,"passed_time":0.8095470826,"remaining_time":0.2418127649},
{"learn":[0.5170195192],"iteration":154,"passed_time":0.8145717893,"remaining_time":0.236488584},
{"learn":[0.5166873554],"iteration":155,"passed_time":0.8197881658,"remaining_time":0.2312223032},
{"learn":[0.516378034],"iteration":156,"passed_time":0.8249877921,"remaining_time":0.2259520704},
{"learn":[0.5160868575],"iteration":157,"passed_time":0.8300017486,"remaining_time":0.2206333762},
{"learn":[0.5157792007],"iteration":158,"passed_time":0.8352967514,"remaining_time":0.2153909862},
{"learn":[0.5153707949],"iteration":159,"passed_time":0.8405432117,"remaining_time":0.2101358029},
{"learn":[0.5150031941],"iteration":160,"passed_time":0.8455411263,"remaining_time":0.2048205213},
{"learn":[0.5147185698],"iteration":161,"passed_time":0.8507981285,"remaining_time":0.1995699314},
{"learn":[0.5143639534],"iteration":162,"passed_time":0.8561135066,"remaining_time":0.1943325138},
{"learn":[0.5140303067],"iteration":163,"passed_time":0.8616173878,"remaining_time":0.1891355241},
{"learn":[0.513687966],"iteration":164,"passed_time":0.8670286841,"remaining_time":0.1839151754},
{"learn":[0.5133414245],"iteration":165,"passed_time":0.8726414837,"remaining_time":0.1787337979},
{"learn":[0.5129930039],"iteration":166,"passed_time":0.878170032,"remaining_time":0.1735306051},
{"learn":[0.5126569732],"iteration":167,"passed_time":0.8833808667,"remaining_time":0.1682630222},
{"learn":[0.512191336],"iteration":168,"passed_time":0.8886497857,"remaining_time":0.1630067654},
{"learn":[0.5118540451],"iteration":169,"passed_time":0.8938914543,"remaining_time":0.1577455508},
{"learn":[0.5115125594],"iteration":170,"passed_time":0.8992227494,"remaining_time":0.1524997645},
{"learn":[0.5112427213],"iteration":171,"passed_time":0.904651796,"remaining_time":0.147268897},
{"learn":[0.5108426773],"iteration":172,"passed_time":0.9099831744,"remaining_time":0.1420204954},
{"learn":[0.5105604444],"iteration":173,"passed_time":0.9152126761,"remaining_time":0.1367559171},
{"learn":[0.5102315674],"iteration":174,"passed_time":0.9206314309,"remaining_time":0.1315187758},
{"learn":[0.5099233027],"iteration":175,"passed_time":0.9261806461,"remaining_time":0.1262973608},
{"learn":[0.5096001617],"iteration":176,"passed_time":0.9310488086,"remaining_time":0.1209837435},
{"learn":[0.5091517004],"iteration":177,"passed_time":0.9359611802,"remaining_time":0.1156805953},
{"learn":[0.5088102749],"iteration":178,"passed_time":0.941239016,"remaining_time":0.110424689},
{"learn":[0.5084640456],"iteration":179,"passed_time":0.9466612292,"remaining_time":0.105184581},
{"learn":[0.5081849376],"iteration":180,"passed_time":0.9518187714,"remaining_time":0.09991467766},
{"learn":[0.5078899833],"iteration":181,"passed_time":0.9568474365,"remaining_time":0.09463326295},
{"learn":[0.5075262436],"iteration":182,"passed_time":0.9623595678,"remaining_time":0.0893995227},
{"learn":[0.5072955206],"iteration":183,"passed_time":0.9675610274,"remaining_time":0.08413574152},
{"learn":[0.5069976515],"iteration":184,"passed_time":0.9724043562,"remaining_time":0.07884359645},
{"learn":[0.5066408066],"iteration":185,"passed_time":0.977559065,"remaining_time":0.07357971457},
{"learn":[0.5063229554],"iteration":186,"passed_time":0.9827595246,"remaining_time":0.06832018086},
{"learn":[0.5060160941],"iteration":187,"passed_time":0.9881584041,"remaining_time":0.06307394069},
{"learn":[0.5057865638],"iteration":188,"passed_time":0.9931633188,"remaining_time":0.05780315612},
{"learn":[0.5054807805],"iteration":189,"passed_time":0.9976236414,"remaining_time":0.05250650744},
{"learn":[0.5051481038],"iteration":190,"passed_time":1.002688599,"remaining_time":0.04724710675},
{"learn":[0.5048612506],"iteration":191,"passed_time":1.008056436,"remaining_time":0.0420023515},
{"learn":[0.5045852829],"iteration":192,"passed_time":1.013201728,"remaining_time":0.0367482492},
{"learn":[0.5042308901],"iteration":193,"passed_time":1.017957139,"remaining_time":0.03148321048},
{"learn":[0.5039030873],"iteration":194,"passed_time":1.023359602,"remaining_time":0.02623998978},
{"learn":[0.5035102606],"iteration":195,"passed_time":1.028836191,"remaining_time":0.02099665695},
{"learn":[0.5032532474],"iteration":196,"passed_time":1.034600076,"remaining_time":0.01575533111},
{"learn":[0.5028852376],"iteration":197,"passed_time":1.03967845,"remaining_time":0.01050180253},
{"learn":[0.5025977767],"iteration":198,"passed_time":1.044837368,"remaining_time":0.005250439033},
{"learn":[0.5023283565],"iteration":199,"passed_time":1.04982974,"remaining_time":0}
]}